{
  "GlobalConfiguration": {
    "ServiceDiscoveryProvider": {
      //"BaseUrl": "http://20.76.221.72:80",
      //"Namespace": "default",
      "Type": "KubernetesServiceDiscoveryProvider"
    }
  },
  "Routes": [
    // Product region
    {
      "UpstreamPathTemplate": "/product",
      "UpstreamHttpMethod": [ "Get" ],
      "DownstreamPathTemplate": "/api/v2/product",
      "DownstreamScheme": "http",
      "DownstreamHostAndPorts": [
        {
          "Host": "ccproductservice-service",
          "Port": 80
        }
      ],
      "SwaggerKey": "product"
    },
    {
      "UpstreamPathTemplate": "/product/{id}",
      "UpstreamHttpMethod": [ "Get" ],
      "DownstreamPathTemplate": "/api/v2/product/{id}",
      "DownstreamScheme": "http",
      "DownstreamHostAndPorts": [
        {
          "Host": "ccproductservice-service",
          "Port": 80
        }
      ],
      "SwaggerKey": "product"
    },
    {
      "UpstreamPathTemplate": "/product",
      "UpstreamHttpMethod": [ "Post" ],
      "DownstreamPathTemplate": "/api/v2/product",
      "DownstreamScheme": "http",
      "DownstreamHostAndPorts": [
        {
          "Host": "ccproductservice-service",
          "Port": 80
        }
      ],
      "SwaggerKey": "product"
    },
    {
      "UpstreamPathTemplate": "/product/{id}",
      "UpstreamHttpMethod": [ "Put" ],
      "DownstreamPathTemplate": "/api/v2/product/{id}",
      "DownstreamScheme": "http",
      "DownstreamHostAndPorts": [
        {
          "Host": "ccproductservice-service",
          "Port": 80
        }
      ],
      "SwaggerKey": "product"
    },
    {
      "UpstreamPathTemplate": "/product/{id}",
      "UpstreamHttpMethod": [ "Patch" ],
      "DownstreamPathTemplate": "/api/v2/product/{id}",
      "DownstreamScheme": "http",
      "DownstreamHostAndPorts": [
        {
          "Host": "ccproductservice-service",
          "Port": 80
        }
      ],
      "SwaggerKey": "product"
    },
    {
      "UpstreamPathTemplate": "/product/{id}",
      "UpstreamHttpMethod": [ "Delete" ],
      "DownstreamPathTemplate": "/api/v2/product/{id}",
      "DownstreamScheme": "http",
      "DownstreamHostAndPorts": [
        {
          "Host": "ccproductservice-service",
          "Port": 80
        }
      ],
      "SwaggerKey": "product"
    },
    {
      "UpstreamPathTemplate": "/product/{id}/categories",
      "UpstreamHttpMethod": [ "Get" ],
      "DownstreamPathTemplate": "/api/v2/product/{id}/categories",
      "DownstreamScheme": "http",
      "DownstreamHostAndPorts": [
        {
          "Host": "ccproductservice-service",
          "Port": 80
        }
      ],
      "SwaggerKey": "product"
    },
    {
      "UpstreamPathTemplate": "/product/{id}/categories",
      "UpstreamHttpMethod": [ "Post" ],
      "DownstreamPathTemplate": "/api/v2/product/{id}/categories",
      "DownstreamScheme": "http",
      "DownstreamHostAndPorts": [
        {
          "Host": "ccproductservice-service",
          "Port": 80
        }
      ],
      "SwaggerKey": "product"
    },
    {
      "UpstreamPathTemplate": "/product/{id}/categories",
      "UpstreamHttpMethod": [ "Put" ],
      "DownstreamPathTemplate": "/api/v2/product/{id}/categories",
      "DownstreamScheme": "http",
      "DownstreamHostAndPorts": [
        {
          "Host": "ccproductservice-service",
          "Port": 80
        }
      ],
      "SwaggerKey": "product"
    },
    {
      "UpstreamPathTemplate": "/product/{id}/taxes",
      "UpstreamHttpMethod": [ "Get" ],
      "DownstreamPathTemplate": "/api/v2/product/{id}/taxes",
      "DownstreamScheme": "http",
      "DownstreamHostAndPorts": [
        {
          "Host": "ccproductservice-service",
          "Port": 80
        }
      ],
      "SwaggerKey": "product"
    },
    {
      "UpstreamPathTemplate": "/product/{id}/taxes",
      "UpstreamHttpMethod": [ "Post" ],
      "DownstreamPathTemplate": "/api/v2/product/{id}/taxes",
      "DownstreamScheme": "http",
      "DownstreamHostAndPorts": [
        {
          "Host": "ccproductservice-service",
          "Port": 80
        }
      ],
      "SwaggerKey": "product"
    },
    {
      "UpstreamPathTemplate": "/product/{id}/taxes",
      "UpstreamHttpMethod": [ "Put" ],
      "DownstreamPathTemplate": "/api/v2/product/{id}/categories",
      "DownstreamScheme": "http",
      "DownstreamHostAndPorts": [
        {
          "Host": "ccproductservice-service",
          "Port": 80
        }
      ],
      "SwaggerKey": "product"
    },
    {
      "UpstreamPathTemplate": "/product/{id}/tags",
      "UpstreamHttpMethod": [ "Get" ],
      "DownstreamPathTemplate": "/api/v2/product/{id}/tags",
      "DownstreamScheme": "http",
      "DownstreamHostAndPorts": [
        {
          "Host": "ccproductservice-service",
          "Port": 80
        }
      ],
      "SwaggerKey": "product"
    },
    {
      "UpstreamPathTemplate": "/product/{id}/tags",
      "UpstreamHttpMethod": [ "Post" ],
      "DownstreamPathTemplate": "/api/v2/product/{id}/tags",
      "DownstreamScheme": "http",
      "DownstreamHostAndPorts": [
        {
          "Host": "ccproductservice-service",
          "Port": 80
        }
      ],
      "SwaggerKey": "product"
    },
    {
      "UpstreamPathTemplate": "/product/{id}/tags",
      "UpstreamHttpMethod": [ "Put" ],
      "DownstreamPathTemplate": "/api/v2/product/{id}/tags",
      "DownstreamScheme": "http",
      "DownstreamHostAndPorts": [
        {
          "Host": "ccproductservice-service",
          "Port": 80
        }
      ],
      "SwaggerKey": "product"
    },
    {
      "UpstreamPathTemplate": "/product/{id}/allergens",
      "UpstreamHttpMethod": [ "Get" ],
      "DownstreamPathTemplate": "/api/v2/product/{id}/allergens",
      "DownstreamScheme": "http",
      "DownstreamHostAndPorts": [
        {
          "Host": "ccproductservice-service",
          "Port": 80
        }
      ],
      "SwaggerKey": "product"
    },
    {
      "UpstreamPathTemplate": "/product/{id}/allergens",
      "UpstreamHttpMethod": [ "Post" ],
      "DownstreamPathTemplate": "/api/v2/product/{id}/allergens",
      "DownstreamScheme": "http",
      "DownstreamHostAndPorts": [
        {
          "Host": "ccproductservice-service",
          "Port": 80
        }
      ],
      "SwaggerKey": "product"
    },
    {
      "UpstreamPathTemplate": "/product/{id}/allergens",
      "UpstreamHttpMethod": [ "Put" ],
      "DownstreamPathTemplate": "/api/v2/product/{id}/allergens",
      "DownstreamScheme": "http",
      "DownstreamHostAndPorts": [
        {
          "Host": "ccproductservice-service",
          "Port": 80
        }
      ],
      "SwaggerKey": "product"
    },
    {
      "UpstreamPathTemplate": "/product/{id}/additives",
      "UpstreamHttpMethod": [ "Get" ],
      "DownstreamPathTemplate": "/api/v2/product/{id}/categories",
      "DownstreamScheme": "http",
      "DownstreamHostAndPorts": [
        {
          "Host": "ccproductservice-service",
          "Port": 80
        }
      ],
      "SwaggerKey": "product"
    },
    {
      "UpstreamPathTemplate": "/product/{id}/additives",
      "UpstreamHttpMethod": [ "Post" ],
      "DownstreamPathTemplate": "/api/v2/product/{id}/categories",
      "DownstreamScheme": "http",
      "DownstreamHostAndPorts": [
        {
          "Host": "ccproductservice-service",
          "Port": 80
        }
      ],
      "SwaggerKey": "product"
    },
    {
      "UpstreamPathTemplate": "/product/{id}/additives",
      "UpstreamHttpMethod": [ "Put" ],
      "DownstreamPathTemplate": "/api/v2/product/{id}/categories",
      "DownstreamScheme": "http",
      "DownstreamHostAndPorts": [
        {
          "Host": "ccproductservice-service",
          "Port": 80
        }
      ],
      "SwaggerKey": "product"
    },
    {
      "UpstreamPathTemplate": "/product/{id}/barcodes",
      "UpstreamHttpMethod": [ "Get" ],
      "DownstreamPathTemplate": "/api/v2/product/{id}/barcodes",
      "DownstreamScheme": "http",
      "DownstreamHostAndPorts": [
        {
          "Host": "ccproductservice-service",
          "Port": 80
        }
      ],
      "SwaggerKey": "product"
    },
    {
      "UpstreamPathTemplate": "/product/{id}/pricings",
      "UpstreamHttpMethod": [ "Get" ],
      "DownstreamPathTemplate": "/api/v2/product/{id}/pricings",
      "DownstreamScheme": "http",
      "DownstreamHostAndPorts": [
        {
          "Host": "ccproductservice-service",
          "Port": 80
        }
      ],
      "SwaggerKey": "product"
    },
    {
      "UpstreamPathTemplate": "/product/{id}/pricings",
      "UpstreamHttpMethod": [ "Post" ],
      "DownstreamPathTemplate": "/api/v2/product/{id}/pricings",
      "DownstreamScheme": "http",
      "DownstreamHostAndPorts": [
        {
          "Host": "ccproductservice-service",
          "Port": 80
        }
      ],
      "SwaggerKey": "product"
    },
    {
      "UpstreamPathTemplate": "/product/{id}/pricings",
      "UpstreamHttpMethod": [ "Put" ],
      "DownstreamPathTemplate": "/api/v2/product/{id}/pricings",
      "DownstreamScheme": "http",
      "DownstreamHostAndPorts": [
        {
          "Host": "ccproductservice-service",
          "Port": 80
        }
      ],
      "SwaggerKey": "product"
    },
    {
      "UpstreamPathTemplate": "/product/{id}/pricings",
      "UpstreamHttpMethod": [ "Delete" ],
      "DownstreamPathTemplate": "/api/v2/product/{id}/pricings",
      "DownstreamScheme": "http",
      "DownstreamHostAndPorts": [
        {
          "Host": "ccproductservice-service",
          "Port": 80
        }
      ],
      "SwaggerKey": "product"
    },
    {
      "UpstreamPathTemplate": "/product/{id}/pricings/history",
      "UpstreamHttpMethod": [ "Get" ],
      "DownstreamPathTemplate": "/api/v2/product/{id}/pricings/history",
      "DownstreamScheme": "http",
      "DownstreamHostAndPorts": [
        {
          "Host": "ccproductservice-service",
          "Port": 80
        }
      ],
      "SwaggerKey": "product"
    },
    // ProductPool region
    {
      "UpstreamPathTemplate": "/productpool",
      "UpstreamHttpMethod": [ "Get" ],
      "DownstreamPathTemplate": "/api/v2/productpool",
      "DownstreamScheme": "http",
      "DownstreamHostAndPorts": [
        {
          "Host": "ccproductpoolservice-service",
          "Port": 80
        }
      ],
      "SwaggerKey": "productpool"
    },
    {
      "UpstreamPathTemplate": "/productpool/{id}",
      "UpstreamHttpMethod": [ "Get" ],
      "DownstreamPathTemplate": "/api/v2/productpool/{id}",
      "DownstreamScheme": "http",
      "DownstreamHostAndPorts": [
        {
          "Host": "ccproductpoolservice-service",
          "Port": 80
        }
      ],
      "SwaggerKey": "productpool"
    },
    {
      "UpstreamPathTemplate": "/productpool",
      "UpstreamHttpMethod": [ "Post" ],
      "DownstreamPathTemplate": "/api/v2/productpool",
      "DownstreamScheme": "http",
      "DownstreamHostAndPorts": [
        {
          "Host": "ccproductpoolservice-service",
          "Port": 80
        }
      ],
      "SwaggerKey": "productpool"
    },
    {
      "UpstreamPathTemplate": "/productpool/{id}",
      "UpstreamHttpMethod": [ "Put" ],
      "DownstreamPathTemplate": "/api/v2/productpool/{id}",
      "DownstreamScheme": "http",
      "DownstreamHostAndPorts": [
        {
          "Host": "ccproductpoolservice-service",
          "Port": 80
        }
      ],
      "SwaggerKey": "productpool"
    },
    {
      "UpstreamPathTemplate": "/productpool/{id}",
      "UpstreamHttpMethod": [ "Patch" ],
      "DownstreamPathTemplate": "/api/v2/productpool/{id}",
      "DownstreamScheme": "http",
      "DownstreamHostAndPorts": [
        {
          "Host": "ccproductpoolservice-service",
          "Port": 80
        }
      ],
      "SwaggerKey": "productpool"
    },
    {
      "UpstreamPathTemplate": "/productpool/{id}",
      "UpstreamHttpMethod": [ "Delete" ],
      "DownstreamPathTemplate": "/api/v2/productpool/{id}",
      "DownstreamScheme": "http",
      "DownstreamHostAndPorts": [
        {
          "Host": "ccproductpoolservice-service",
          "Port": 80
        }
      ],
      "SwaggerKey": "productpool"
    },
    // CategoryPool
    {
      "UpstreamPathTemplate": "/categorypool",
      "UpstreamHttpMethod": [ "Get" ],
      "DownstreamPathTemplate": "/api/v2/categorypool",
      "DownstreamScheme": "http",
      "DownstreamHostAndPorts": [
        {
          "Host": "cccategoryservice-service",
          "Port": 80
        }
      ],
      "SwaggerKey": "categoryPool"
    },
    {
      "UpstreamPathTemplate": "/categorypool/{id}",
      "UpstreamHttpMethod": [ "Get" ],
      "DownstreamPathTemplate": "/api/v2/categorypool/{id}",
      "DownstreamScheme": "http",
      "DownstreamHostAndPorts": [
        {
          "Host": "cccategoryservice-service",
          "Port": 80
        }
      ],
      "SwaggerKey": "categoryPool"
    },
    {
      "UpstreamPathTemplate": "/categorypool",
      "UpstreamHttpMethod": [ "Post" ],
      "DownstreamPathTemplate": "/api/v2/categorypool",
      "DownstreamScheme": "http",
      "DownstreamHostAndPorts": [
        {
          "Host": "cccategoryservice-service",
          "Port": 80
        }
      ],
      "SwaggerKey": "categoryPool"
    },
    {
      "UpstreamPathTemplate": "/categorypool/{id}",
      "UpstreamHttpMethod": [ "Put" ],
      "DownstreamPathTemplate": "/api/v2/categorypool/{id}",
      "DownstreamScheme": "http",
      "DownstreamHostAndPorts": [
        {
          "Host": "cccategoryservice-service",
          "Port": 80
        }
      ],
      "SwaggerKey": "categoryPool"
    },
    {
      "UpstreamPathTemplate": "/categorypool/{id}",
      "UpstreamHttpMethod": [ "Patch" ],
      "DownstreamPathTemplate": "/api/v2/categorypool/{id}",
      "DownstreamScheme": "http",
      "DownstreamHostAndPorts": [
        {
          "Host": "cccategoryservice-service",
          "Port": 80
        }
      ],
      "SwaggerKey": "categoryPool"
    },
    {
      "UpstreamPathTemplate": "/categorypool/{id}",
      "UpstreamHttpMethod": [ "Delete" ],
      "DownstreamPathTemplate": "/api/v2/categorypool/{id}",
      "DownstreamScheme": "http",
      "DownstreamHostAndPorts": [
        {
          "Host": "cccategoryservice-service",
          "Port": 80
        }
      ],
      "SwaggerKey": "categoryPool"
    },
    // Category
    {
      "UpstreamPathTemplate": "/category",
      "UpstreamHttpMethod": [ "Get" ],
      "DownstreamPathTemplate": "/api/v2/category",
      "DownstreamScheme": "http",
      "DownstreamHostAndPorts": [
        {
          "Host": "cccategoryservice-service",
          "Port": 80
        }
      ],
      "SwaggerKey": "category"
    },
    {
      "UpstreamPathTemplate": "/category/{id}",
      "UpstreamHttpMethod": [ "Get" ],
      "DownstreamPathTemplate": "/api/v2/category/{id}",
      "DownstreamScheme": "http",
      "DownstreamHostAndPorts": [
        {
          "Host": "cccategoryservice-service",
          "Port": 80
        }
      ],
      "SwaggerKey": "category"
    },
    {
      "UpstreamPathTemplate": "/category",
      "UpstreamHttpMethod": [ "Post" ],
      "DownstreamPathTemplate": "/api/v2/category",
      "DownstreamScheme": "http",
      "DownstreamHostAndPorts": [
        {
          "Host": "cccategoryservice-service",
          "Port": 80
        }
      ],
      "SwaggerKey": "category"
    },
    {
      "UpstreamPathTemplate": "/category/{id}",
      "UpstreamHttpMethod": [ "Put" ],
      "DownstreamPathTemplate": "/api/v2/category/{id}",
      "DownstreamScheme": "http",
      "DownstreamHostAndPorts": [
        {
          "Host": "cccategoryservice-service",
          "Port": 80
        }
      ],
      "SwaggerKey": "category"
    },
    {
      "UpstreamPathTemplate": "/category/{id}",
      "UpstreamHttpMethod": [ "Patch" ],
      "DownstreamPathTemplate": "/api/v2/category/{id}",
      "DownstreamScheme": "http",
      "DownstreamHostAndPorts": [
        {
          "Host": "cccategoryservice-service",
          "Port": 80
        }
      ],
      "SwaggerKey": "category"
    },
    {
      "UpstreamPathTemplate": "/category/{id}",
      "UpstreamHttpMethod": [ "Delete" ],
      "DownstreamPathTemplate": "/api/v2/category/{id}",
      "DownstreamScheme": "http",
      "DownstreamHostAndPorts": [
        {
          "Host": "cccategoryservice-service",
          "Port": 80
        }
      ],
      "SwaggerKey": "category"
    },
    // ProductPriceList
    {
      "UpstreamPathTemplate": "/productpricelist",
      "UpstreamHttpMethod": [ "Get" ],
      "DownstreamPathTemplate": "/api/v2/productpricelist",
      "DownstreamScheme": "http",
      "DownstreamHostAndPorts": [
        {
          "Host": "ccproductpriceservice-service",
          "Port": 80
        }
      ],
      "SwaggerKey": "productpricelist"
    },
    {
      "UpstreamPathTemplate": "/productpricelist/{id}",
      "UpstreamHttpMethod": [ "Get" ],
      "DownstreamPathTemplate": "/api/v2/productpricelist/{id}",
      "DownstreamScheme": "http",
      "DownstreamHostAndPorts": [
        {
          "Host": "ccproductpriceservice-service",
          "Port": 80
        }
      ],
      "SwaggerKey": "productpricelist"
    },
    {
      "UpstreamPathTemplate": "/productpricelist",
      "UpstreamHttpMethod": [ "Post" ],
      "DownstreamPathTemplate": "/api/v2/productpricelist",
      "DownstreamScheme": "http",
      "DownstreamHostAndPorts": [
        {
          "Host": "ccproductpriceservice-service",
          "Port": 80
        }
      ],
      "SwaggerKey": "productpricelist"
    },
    {
      "UpstreamPathTemplate": "/productpricelist/{id}",
      "UpstreamHttpMethod": [ "Put" ],
      "DownstreamPathTemplate": "/api/v2/productpricelist/{id}",
      "DownstreamScheme": "http",
      "DownstreamHostAndPorts": [
        {
          "Host": "ccproductpriceservice-service",
          "Port": 80
        }
      ],
      "SwaggerKey": "productpricelist"
    },
    {
      "UpstreamPathTemplate": "/productpricelist/{id}",
      "UpstreamHttpMethod": [ "Patch" ],
      "DownstreamPathTemplate": "/api/v2/productpricelist/{id}",
      "DownstreamScheme": "http",
      "DownstreamHostAndPorts": [
        {
          "Host": "ccproductpriceservice-service",
          "Port": 80
        }
      ],
      "SwaggerKey": "productpricelist"
    },
    {
      "UpstreamPathTemplate": "/productpricelist/{id}",
      "UpstreamHttpMethod": [ "Delete" ],
      "DownstreamPathTemplate": "/api/v2/productpricelist/{id}",
      "DownstreamScheme": "http",
      "DownstreamHostAndPorts": [
        {
          "Host": "ccproductpriceservice-service",
          "Port": 80
        }
      ],
      "SwaggerKey": "productpricelist"
    },
    // ProductPricePool
    {
      "UpstreamPathTemplate": "/productpricepool",
      "UpstreamHttpMethod": [ "Get" ],
      "DownstreamPathTemplate": "/api/v2/productpricepool",
      "DownstreamScheme": "http",
      "DownstreamHostAndPorts": [
        {
          "Host": "ccproductpriceservice-service",
          "Port": 80
        }
      ],
      "SwaggerKey": "productpricepool"
    },
    {
      "UpstreamPathTemplate": "/productpricepool/{id}",
      "UpstreamHttpMethod": [ "Get" ],
      "DownstreamPathTemplate": "/api/v2/productpricepool/{id}",
      "DownstreamScheme": "http",
      "DownstreamHostAndPorts": [
        {
          "Host": "ccproductpriceservice-service",
          "Port": 80
        }
      ],
      "SwaggerKey": "productpricepool"
    },
    {
      "UpstreamPathTemplate": "/productpricepool",
      "UpstreamHttpMethod": [ "Post" ],
      "DownstreamPathTemplate": "/api/v2/productpricepool",
      "DownstreamScheme": "http",
      "DownstreamHostAndPorts": [
        {
          "Host": "ccproductpriceservice-service",
          "Port": 80
        }
      ],
      "SwaggerKey": "productpricepool"
    },
    {
      "UpstreamPathTemplate": "/productpricepool/{id}",
      "UpstreamHttpMethod": [ "Put" ],
      "DownstreamPathTemplate": "/api/v2/productpricepool/{id}",
      "DownstreamScheme": "http",
      "DownstreamHostAndPorts": [
        {
          "Host": "ccproductpriceservice-service",
          "Port": 80
        }
      ],
      "SwaggerKey": "productpricepool"
    },
    {
      "UpstreamPathTemplate": "/productpricepool/{id}",
      "UpstreamHttpMethod": [ "Patch" ],
      "DownstreamPathTemplate": "/api/v2/productpricepool/{id}",
      "DownstreamScheme": "http",
      "DownstreamHostAndPorts": [
        {
          "Host": "ccproductpriceservice-service",
          "Port": 80
        }
      ],
      "SwaggerKey": "productpricepool"
    },
    {
      "UpstreamPathTemplate": "/productpricepool/{id}",
      "UpstreamHttpMethod": [ "Delete" ],
      "DownstreamPathTemplate": "/api/v2/productpricepool/{id}",
      "DownstreamScheme": "http",
      "DownstreamHostAndPorts": [
        {
          "Host": "ccproductpriceservice-service",
          "Port": 80
        }
      ],
      "SwaggerKey": "productpricepool"
    },
    // AuthServer
    {
      "UpstreamPathTemplate": "/authorize",
      "DownstreamPathTemplate": "/home/authorize",
      "DownstreamScheme": "http",
      "DownstreamHostAndPorts": [
        {
          "Host": "ccauthserver-service",
          "Port": 80
        }
      ]
    },
    {
      "UpstreamPathTemplate": "/token",
      "DownstreamPathTemplate": "/home/token",
      "DownstreamScheme": "http",
      "DownstreamHostAndPorts": [
        {
          "Host": "ccauthserver-service",
          "Port": 80
        }
      ]
    },
    {
      "UpstreamPathTemplate": "/systems",
      "DownstreamPathTemplate": "/home/GetSystems",
      "DownstreamScheme": "http",
      "DownstreamHostAndPorts": [
        {
          "Host": "ccauthserver-service",
          "Port": 80
        }
      ]
    },
    {
      "UpstreamPathTemplate": "/home/login",
      "UpstreamHttpMethod": [ "Get" ],
      "DownstreamPathTemplate": "/home/login",
      "DownstreamScheme": "http",
      "DownstreamHostAndPorts": [
        {
          "Host": "ccauthserver-service",
          "Port": 80
        }
      ]
    },
    {
      "UpstreamPathTemplate": "/home/login",
      "UpstreamHttpMethod": [ "Post" ],
      "DownstreamPathTemplate": "/home/login",
      "DownstreamScheme": "http",
      "DownstreamHostAndPorts": [
        {
          "Host": "ccauthserver-service",
          "Port": 80
        }
      ]
    }
  ],
  "SwaggerEndPoints": [
    {
      "Key": "product",
      "Config": [
        {
          "Name": "CCProductService",
          "Version": "v2",
          "Url": "http://ccproductservice-service:80/swagger/v2/swagger.json"
        }
      ]
    },
    {
      "Key": "productpool",
      "Config": [
        {
          "Name": "CCProductPoolService",
          "Version": "v2",
          "Url": "http://ccproductpoolservice-service:80/swagger/v2/swagger.json"
        }
      ]
    },
    {
      "Key": "categoryPool",
      "Config": [
        {
          "Name": "CCCategoryPoolService",
          "Version": "v2",
          "Url": "http://cccategoryservice-service:80/swagger/v2/swagger.json"
        }
      ]
    },
    {
      "Key": "category",
      "Config": [
        {
          "Name": "CCCategoryService",
          "Version": "v2",
          "Url": "http://cccategoryservice-service:80/swagger/v2/swagger.json"
        }
      ]
    },
    {
      "Key": "productpricelist",
      "Config": [
        {
          "Name": "CCProductPriceListService",
          "Version": "v2",
          "Url": "http://ccproductpriceservice-service:80/swagger/v2/swagger.json"
        }
      ]
    },
    {
      "Key": "productpricepool",
      "Config": [
        {
          "Name": "CCProductPricePoolService",
          "Version": "v2",
          "Url": "http://ccproductpriceservice-service:80/swagger/v2/swagger.json"
        }
      ]
    }
  ]
}
